hcli_hg/__init__.py
hcli_hg/__main__.py
hcli_hg/config.py
hcli_hg/hutils.py
hcli_hg/package.py
hcli_hg/cli/__init__.py
hcli_hg/cli/chat.output
hcli_hg/cli/cli.py
hcli_hg/cli/context.json
hcli_hg/cli/instance.py
hcli_hg/cli/logger.py
hcli_hg/cli/template.json
hcli_hg/data/hcli_hg.1
hcli_hg-0.1.6.dist-info/LICENSE.txt
hcli_hg-0.1.6.dist-info/METADATA
hcli_hg-0.1.6.dist-info/WHEEL
hcli_hg-0.1.6.dist-info/entry_points.txt
hcli_hg-0.1.6.dist-info/top_level.txt
hcli_hg-0.1.6.dist-info/RECORD
