Metadata-Version: 2.1
Name: hcli-hg
Version: 0.1.6
Summary: HCLI hg is a python package wrapper that contains an HCLI sample application (hg); hg is an HCLI for interacting with GPT-3.5-Turbo via terminal input and output streams.
Home-page: https://github.com/cometaj2/hcli_hg
Author: Jeff Michaud
Author-email: cometaj2@comcast.net
License: MIT
Keywords: cli client server connector hypermedia rest generic development
Classifier: Development Status :: 2 - Pre-Alpha
Classifier: Intended Audience :: Developers
Classifier: Topic :: Software Development
Classifier: License :: OSI Approved :: MIT License
Classifier: Programming Language :: Python :: 3.8
Classifier: Programming Language :: Python :: 3.9
Classifier: Programming Language :: Python :: 3.10
Classifier: Programming Language :: Python :: 3.11
License-File: LICENSE.txt
Requires-Dist: openai (==1.7.0)
Requires-Dist: tiktoken (==0.5.2)
